golden_frame/assets/big_frame.jpg
golden_frame/assets/big_frame.json
golden_frame/assets/golden_frame.json
golden_frame/assets/golden_frame.png
golden_frame/assets/obamium_portrait.jpg
golden_frame/assets/obamium_portrait.json
golden_frame/assets/orz.jpg
golden_frame/assets/orz.json
golden_frame/assets/schizo.jpg
golden_frame/assets/schizo.json
golden_frame/assets/soldier_meme.jpg
golden_frame/assets/soldier_meme.json
golden_frame/assets/vladdy_daddy.jpg
golden_frame/assets/vladdy_daddy.json
golden_frame/assets/wessuwan.json
golden_frame/assets/wessuwan.png
golden_frame/cli.py
golden_frame/lib.py
golden_frame-2.1.74.dist-info/LICENSE
golden_frame-2.1.74.dist-info/METADATA
golden_frame-2.1.74.dist-info/WHEEL
golden_frame-2.1.74.dist-info/entry_points.txt
golden_frame-2.1.74.dist-info/RECORD
