Metadata-Version: 2.1
Name: golden-frame
Version: 2.1.74
Summary: Golden Frame "กรอบทอง" Generator, Create Golden Frame for given images (Also supports other frame, included with selected quality frames)
Home-page: https://github.com/leomotors/golden-frame
License: MIT
Keywords: meme,meme-generator
Author: Nutthapat Pongtanyavichai
Author-email: 59821765+Leomotors@users.noreply.github.com
Requires-Python: >=3.9,<4.0
Classifier: License :: OSI Approved :: MIT License
Classifier: Programming Language :: Python :: 3
Classifier: Programming Language :: Python :: 3.9
Classifier: Programming Language :: Python :: 3.10
Classifier: Programming Language :: Python :: 3.11
Classifier: Programming Language :: Python :: 3.12
Requires-Dist: numpy (>=1.26.2,<2.0.0)
Requires-Dist: opencv-python (>=4.8.1.78,<5.0.0.0)
Requires-Dist: typer (>=0.9.0,<0.10.0)
Project-URL: Repository, https://github.com/leomotors/golden-frame
